logmaster/__init__.py
logmaster/logmaster.py
logmaster_pro-1.0.2.dist-info/licenses/LICENSE
logmaster_pro-1.0.2.dist-info/METADATA
logmaster_pro-1.0.2.dist-info/WHEEL
logmaster_pro-1.0.2.dist-info/top_level.txt
logmaster_pro-1.0.2.dist-info/RECORD
