Metadata-Version: 2.4
Name: logmaster-pro
Version: 1.0.2
Summary: Advanced colorful logger with caller tracking
Author-email: Lalit Pal <happytaak8@gmail.com>
License: MIT
Project-URL: Repository, https://github.com/Lalit2206/logmaster-pro
Classifier: Programming Language :: Python :: 3
Classifier: Programming Language :: Python :: 3.8
Classifier: License :: OSI Approved :: MIT License
Classifier: Operating System :: OS Independent
Classifier: Intended Audience :: Developers
Classifier: Topic :: Software Development :: Libraries :: Python Modules
Classifier: Topic :: System :: Logging
Requires-Python: >=3.8
License-File: LICENSE
Dynamic: license-file
